miniml/__init__.py
miniml/loss.py
miniml/model.py
miniml/nn/__init__.py
miniml/nn/activations.py
miniml/nn/compose.py
miniml/nn/dropout.py
miniml/nn/embedding.py
miniml/nn/layer_norm.py
miniml/nn/linear.py
miniml/nn/mha.py
miniml/nn/mlp.py
miniml/nn/ortho.py
miniml/nn/positional.py
miniml/nn/rbf.py
miniml/nn/rbfnet.py
miniml/optim/__init__.py
miniml/optim/adam.py
miniml/optim/base.py
miniml/optim/scipy.py
miniml/param.py
miniml/random.py
miniml/utils.py
miniml_jax-0.7.0.dist-info/WHEEL
miniml_jax-0.7.0.dist-info/METADATA
miniml_jax-0.7.0.dist-info/RECORD
