Metadata-Version: 2.3
Name: miniml-jax
Version: 0.7.0
Summary: MiniML - a minimalistic ML framework
Requires-Dist: jax>=0.8.0
Requires-Dist: numpy>=2.3.4
Requires-Dist: scipy>=1.16.1
Requires-Dist: typing-extensions>=4.15.0 ; python_full_version < '3.11'
Requires-Dist: jax[cuda]>=0.8.0 ; extra == 'cuda'
Requires-Python: >=3.12
Project-URL: Documentation, https://stur86.github.io/miniml/
Project-URL: Repository, https://github.com/stur86/miniml
Provides-Extra: cuda
